Metadata-Version: 1.0
Name: e.calc
Version: 1.0.0
Summary: Small calculator package
Home-page: UNKNOWN
Author: Wiktor Skrzynecki
Author-email: errorflin@gmail.com
License: MIT
Keywords: calculator
Platform: UNKNOWN
